microlab/__init__.py
microlab/__main__.py
microlab/types.py
microlab/analysis/__init__.py
microlab/analysis/analysis.py
microlab/cryptography/__init__.py
microlab/cryptography/asymmetric.py
microlab/cryptography/symmetric.py
microlab/examples/__init__.py
microlab/examples/api.py
microlab/examples/cryptography/__init__.py
microlab/examples/cryptography/asymmetric.py
microlab/examples/cryptography/symmetric.py
microlab/examples/geometry/__init__.py
microlab/examples/geometry/line.py
microlab/examples/geometry/points.py
microlab/examples/geometry/polygon.py
microlab/examples/hardware/__init__.py
microlab/examples/io/__init__.py
microlab/examples/io/csv_C.R.U.D.py
microlab/examples/io/file_C.R.U.D.py
microlab/examples/io/json_C.R.U.D.py
microlab/examples/io/yaml_C.R.U.D.py
microlab/examples/io/zip_C.R.U.D.py
microlab/examples/methods/Intersection.py
microlab/examples/methods/__init__.py
microlab/examples/methods/interpolation.py
microlab/examples/plots/__init__.py
microlab/examples/plots/plot_1d.py
microlab/examples/plots/plot_2d.py
microlab/examples/signals/1d.py
microlab/examples/signals/2d.py
microlab/examples/signals/__init__.py
microlab/examples/software/__init__.py
microlab/examples/software/details.py
microlab/examples/types/Types.py
microlab/examples/types/__init__.py
microlab/examples/vision/__init__.py
microlab/examples/vision/edit.py
microlab/examples/vision/momments.py
microlab/examples/vision/record.py
microlab/geometry/__init__.py
microlab/geometry/lines.py
microlab/geometry/points.py
microlab/geometry/polygons.py
microlab/hardware/__init__.py
microlab/hardware/cpu.py
microlab/hardware/ram.py
microlab/io/__init__.py
microlab/io/csv.py
microlab/io/files.py
microlab/io/folders.py
microlab/io/images.py
microlab/io/json.py
microlab/io/yaml.py
microlab/io/zip.py
microlab/methods/__init__.py
microlab/methods/interpolation.py
microlab/methods/intersection.py
microlab/network/__init__.py
microlab/plots/__init__.py
microlab/plugins/__init__.py
microlab-0.4.6.dist-info/LICENSE
microlab-0.4.6.dist-info/METADATA
microlab-0.4.6.dist-info/WHEEL
microlab-0.4.6.dist-info/top_level.txt
microlab-0.4.6.dist-info/RECORD
