Metadata-Version: 2.1
Name: microlab
Version: 0.4.6
Summary: A lab analysis node
Home-page: https://github.com/alexnicolaou/
Author: Alex nicolaou
Author-email: lialiaou@gmail.com
License: demo project
Requires-Dist: numpy
Requires-Dist: pandas
Requires-Dist: scipy
Requires-Dist: matplotlib
Requires-Dist: patool
Requires-Dist: playsound
Requires-Dist: cryptography
Requires-Dist: opencv-contrib-python
Requires-Dist: shapely
Requires-Dist: django
